<role scriptid="customrolecustomrole_abacus_integration">
  <centertype>[scriptid=custcenter8]</centertype>
  <coreadminpermission>F</coreadminpermission>
  <custrecord_dunning_role_flag></custrecord_dunning_role_flag>
  <employeerestriction>NONE</employeerestriction>
  <employeeselectionunrestricted>F</employeeselectionunrestricted>
  <isinactive>F</isinactive>
  <issalesrole>F</issalesrole>
  <issinglesignononly>F</issinglesignononly>
  <issupportrole>F</issupportrole>
  <iswebserviceonlyrole>F</iswebserviceonlyrole>
  <name>Abacus Integration</name>
  <parentrolescriptid></parentrolescriptid>
  <restrictbydevice>F</restrictbydevice>
  <subsidiaryoption>ALL</subsidiaryoption>
  <subsidiaryviewingallowed>T</subsidiaryviewingallowed>
  <tfaduration>0</tfaduration>
  <tfarequired>OFF</tfarequired>
  <permissions>
    <permission>
      <permkey>TRAN_VENDBILL</permkey>
      <permlevel>CREATE</permlevel>
    </permission>
    <permission>
      <permkey>TRAN_CARDCHRG</permkey>
      <permlevel>CREATE</permlevel>
    </permission>
    <permission>
      <permkey>TRAN_CARDRFND</permkey>
      <permlevel>CREATE</permlevel>
    </permission>
    <permission>
      <permkey>TRAN_FIND</permkey>
      <permlevel>VIEW</permlevel>
    </permission>
    <permission>
      <permkey>TRAN_JOURNALAPPRV</permkey>
      <permlevel>FULL</permlevel>
    </permission>
    <permission>
      <permkey>TRAN_JOURNAL</permkey>
      <permlevel>CREATE</permlevel>
    </permission>
    <permission>
      <permkey>TRAN_VENDPYMT</permkey>
      <permlevel>CREATE</permlevel>
    </permission>
    <permission>
      <permkey>TRAN_VENDBILLAPPRV</permkey>
      <permlevel>FULL</permlevel>
    </permission>
    <permission>
      <permkey>LIST_ACCOUNT</permkey>
      <permlevel>CREATE</permlevel>
    </permission>
    <permission>
      <permkey>LIST_OTHER_ADDRESS</permkey>
      <permlevel>FULL</permlevel>
    </permission>
    <permission>
      <permkey>LIST_AMORTIZATION</permkey>
      <permlevel>VIEW</permlevel>
    </permission>
    <permission>
      <permkey>LIST_BULK_PROCESSING</permkey>
      <permlevel>VIEW</permlevel>
    </permission>
    <permission>
      <permkey>LIST_CLASS</permkey>
      <permlevel>VIEW</permlevel>
    </permission>
    <permission>
      <permkey>LIST_COMPANY</permkey>
      <permlevel>VIEW</permlevel>
    </permission>
    <permission>
      <permkey>LIST_DEPARTMENT</permkey>
      <permlevel>VIEW</permlevel>
    </permission>
    <permission>
      <permkey>LIST_EMPLOYEE_RECORD</permkey>
      <permlevel>VIEW</permlevel>
    </permission>
    <permission>
      <permkey>LIST_EMPLOYEE</permkey>
      <permlevel>VIEW</permlevel>
    </permission>
    <permission>
      <permkey>LIST_LOCATION</permkey>
      <permlevel>VIEW</permlevel>
    </permission>
    <permission>
      <permkey>LIST_OTHERNAME</permkey>
      <permlevel>CREATE</permlevel>
    </permission>
    <permission>
      <permkey>LIST_SUBSIDIARY</permkey>
      <permlevel>VIEW</permlevel>
    </permission>
    <permission>
      <permkey>LIST_TAXITEM</permkey>
      <permlevel>VIEW</permlevel>
    </permission>
    <permission>
      <permkey>LIST_VENDOR</permkey>
      <permlevel>CREATE</permlevel>
    </permission>
    <permission>
      <permkey>ADMI_CUSTCOLUMNFIELD</permkey>
      <permlevel>VIEW</permlevel>
    </permission>
    <permission>
      <permkey>ADMI_CUSTLIST</permkey>
      <permlevel>VIEW</permlevel>
    </permission>
    <permission>
      <permkey>ADMI_CUSTRECORD</permkey>
      <permlevel>VIEW</permlevel>
    </permission>
    <permission>
      <permkey>ADMI_LOGIN_OAUTH</permkey>
      <permlevel>FULL</permlevel>
    </permission>
    <permission>
      <permkey>ADMI_LOGIN_OAUTH2</permkey>
      <permlevel>FULL</permlevel>
    </permission>
    <permission>
      <permkey>ADMI_ACCTPERIODS</permkey>
      <permlevel>VIEW</permlevel>
    </permission>
    <permission>
      <permkey>ADMI_WEBSERVICES</permkey>
      <permlevel>FULL</permlevel>
    </permission>
    <permission>
      <permkey>ADMI_CUSTOMSCRIPT</permkey>
      <permlevel>VIEW</permlevel>
    </permission>
    <permission>
      <permkey>ADMI_MANAGE_OWN_OAUTH_TOKENS</permkey>
      <permlevel>FULL</permlevel>
    </permission>
    <permission>
      <permkey>ADMI_VICARIOUS_EMAILS</permkey>
      <permlevel>FULL</permlevel>
    </permission>
  </permissions>
</role>